hivemind_core/__init__.py
hivemind_core/__main__.py
hivemind_core/config.py
hivemind_core/database.py
hivemind_core/protocol.py
hivemind_core/scripts.py
hivemind_core/service.py
hivemind_core/version.py
hivemind_core-4.0.0.dist-info/licenses/LICENSE
hivemind_core-4.0.0.dist-info/METADATA
hivemind_core-4.0.0.dist-info/WHEEL
hivemind_core-4.0.0.dist-info/entry_points.txt
hivemind_core-4.0.0.dist-info/top_level.txt
hivemind_core-4.0.0.dist-info/RECORD
