Metadata-Version: 2.4
Name: hivemind-core
Version: 4.0.0
Summary: Mesh Networking utilities for OpenVoiceOS
Home-page: https://github.com/JarbasHiveMind/HiveMind-core
Author: jarbasAI
Author-email: jarbasai@mailfence.com
License: AGPL-3.0
License-File: LICENSE
Requires-Dist: click
Requires-Dist: click_default_group
Requires-Dist: rich
Requires-Dist: pycryptodomex
Requires-Dist: poorman-handshake<2.0.0,>=1.0.1
Requires-Dist: hivemind_bus_client<1.0.0,>=0.2.0
Requires-Dist: ovos_utils<1.0.0,>=0.0.33
Requires-Dist: pybase64
Requires-Dist: hivemind-plugin-manager<1.0.0,>=0.3.0
Requires-Dist: ovos-bus-client<2.0.0,>=1.3.1
Requires-Dist: json-database<1.0.0,>=0.9.1
Requires-Dist: hivemind-websocket-protocol<1.0.0,>=0.0.3
Requires-Dist: setuptools
Dynamic: author
Dynamic: author-email
Dynamic: home-page
Dynamic: license
Dynamic: license-file
Dynamic: requires-dist
Dynamic: summary
